cctxpa/__init__.py
cctxpa/cctxpa.py
cctxpa/report.py
cctxpa/pcap_extractor/DNSExtractor.py
cctxpa/pcap_extractor/Extractor.py
cctxpa/pcap_extractor/FlowBase.py
cctxpa/pcap_extractor/FlowExtractor.py
cctxpa/pcap_extractor/HTTPParser.py
cctxpa/pcap_extractor/ICMPExtractor.py
cctxpa/pcap_extractor/IMAPParser.py
cctxpa/pcap_extractor/MyEncoder.py
cctxpa/pcap_extractor/POP3Parser.py
cctxpa/pcap_extractor/SMTPParser.py
cctxpa/pcap_extractor/TCPFlow.py
cctxpa/pcap_extractor/__init__.py
cctxpa/pcap_extractor/mail.py
cctxpa-0.2.7.dist-info/METADATA
cctxpa-0.2.7.dist-info/WHEEL
cctxpa-0.2.7.dist-info/entry_points.txt
cctxpa-0.2.7.dist-info/top_level.txt
cctxpa-0.2.7.dist-info/zip-safe
cctxpa-0.2.7.dist-info/RECORD
